aenv/__init__.py
aenv/main.py
aenv/client/__init__.py
aenv/client/scheduler_client.py
aenv/core/__init__.py
aenv/core/environment.py
aenv/core/exceptions.py
aenv/core/function_registry.py
aenv/core/logging.py
aenv/core/mcp_health.py
aenv/core/mcp_tool.py
aenv/core/models.py
aenv/core/tool.py
aenv/server/__init__.py
aenv/server/mcp_server.py
aenv/tests/__init__.py
aenv/tests/test_environment.py
aenv/tests/test_health.py
aenv/tests/test_search_env.py
aenv/tests/test_terminal_env.py
aenv/tests/test_tool.py
aenv/tests/test_weather_env.py
cli/__init__.py
cli/cli.py
cli/client/__init__.py
cli/client/aenv_hub_client.py
cli/cmds/__init__.py
cli/cmds/build.py
cli/cmds/common.py
cli/cmds/config.py
cli/cmds/get.py
cli/cmds/init.py
cli/cmds/instance.py
cli/cmds/list.py
cli/cmds/pull.py
cli/cmds/push.py
cli/cmds/run.py
cli/cmds/service.py
cli/cmds/version.py
cli/data/version_info.json
cli/extends/artifacts/__init__.py
cli/extends/artifacts/artifacts_builder.py
cli/extends/storage/__init__.py
cli/extends/storage/storage_manager.py
cli/templates/README.md
cli/templates/default/Dockerfile
cli/templates/default/config.json
cli/templates/default/requirements.txt
cli/templates/default/src/__init__.py
cli/templates/default/src/custom_env.py
cli/tests/__init__.py
cli/tests/test_build_cmd.py
cli/tests/test_cmds.py
cli/tests/test_env_hub.py
cli/tests/test_instances.py
cli/tests/test_singleton.py
cli/utils/__init__.py
cli/utils/api_helpers.py
cli/utils/archive_tool.py
cli/utils/cli_config.py
cli/utils/config.py
cli/utils/oss_client.py
cli/utils/scaffold.py
cli/utils/table_formatter.py
cli/utils/common/__init__.py
cli/utils/common/aenv_logger.py
cli/utils/common/console.py
cli/utils/mcp/__init__.py
cli/utils/mcp/mcp_inspector.py
cli/utils/mcp/mcp_task_manager.py
aenvironment-0.1.4.dist-info/METADATA
aenvironment-0.1.4.dist-info/WHEEL
aenvironment-0.1.4.dist-info/entry_points.txt
aenvironment-0.1.4.dist-info/top_level.txt
aenvironment-0.1.4.dist-info/RECORD
