Metadata-Version: 2.4
Name: aenvironment
Version: 0.1.4
Summary: AEnvironment Python SDK - Production-grade environment for AI agent tools
Author: AEnvironment Team
License: Apache-2.0
Project-URL: Homepage, https://github.com/inclusionAI/AEnvironment
Project-URL: Repository, https://github.com/inclusionAI/AEnvironment
Project-URL: Documentation, https://inclusionai.github.io/AEnvironment
Keywords: ai,agent,tools,mcp,environment
Classifier: Development Status :: 4 - Beta
Classifier: Intended Audience :: Developers
Classifier: License :: OSI Approved :: Apache Software License
Classifier: Programming Language :: Python :: 3
Classifier: Programming Language :: Python :: 3.10
Classifier: Programming Language :: Python :: 3.12
Requires-Python: >=3.10
Requires-Dist: pydantic>=1.10.0
Requires-Dist: httpx>=0.20.0
Requires-Dist: anyio>=3.0.0
Requires-Dist: typing-extensions>=4.0.0
Requires-Dist: mcp>=1.0.0
Requires-Dist: uvicorn>=0.20.0
Requires-Dist: click>=8.0.0
Requires-Dist: requests>=2.25.0
Requires-Dist: fastmcp>=2.13.0
Requires-Dist: rich>=13.0.0
Requires-Dist: typer>=0.9.0
Requires-Dist: tabulate>=0.9.0
Requires-Dist: colorlog>=6.10.1
Requires-Dist: openai-agents>=0.6.3
Requires-Dist: starlette>=0.27.0
Requires-Dist: urllib3>=1.26.0
Requires-Dist: docker>=6.0.0
Provides-Extra: dev
Requires-Dist: pytest>=7.0.0; extra == "dev"
Requires-Dist: pytest-asyncio>=0.21.0; extra == "dev"
Requires-Dist: black>=22.0.0; extra == "dev"
Requires-Dist: isort>=5.10.0; extra == "dev"
Requires-Dist: mypy>=1.0.0; extra == "dev"
Requires-Dist: ruff>=0.1.0; extra == "dev"
Provides-Extra: docs
Requires-Dist: jupyter-book<2; extra == "docs"
Requires-Dist: sphinxcontrib.mermaid==1.2.3; extra == "docs"
